inductive/__init__.py
inductive/builtins.py
inductive/config.py
inductive/nat.py
inductive/py.typed
inductive-0.0.1.post1.dist-info/LICENSE
inductive-0.0.1.post1.dist-info/METADATA
inductive-0.0.1.post1.dist-info/WHEEL
inductive-0.0.1.post1.dist-info/top_level.txt
inductive-0.0.1.post1.dist-info/RECORD
