Metadata-Version: 2.1
Name: inductive
Version: 0.0.1.post1
Summary: Inductive data structures for Python
Author-email: Lexa <contact@qexat.com>
License: MIT License
Project-URL: source, https://github.com/qexat/inductive
Keywords: inductive,data structures,nat,natural numbers,list,linked list,dependent typing
Requires-Python: >=3.12
License-File: LICENSE
Requires-Dist: attrs<25,>=24
Requires-Dist: result<0.18,>=0.17
Requires-Dist: option-python<0.1,>=0.0.2
Provides-Extra: dev
Requires-Dist: build<1.3,>=1.2; extra == "dev"
Requires-Dist: coverage<8,>=7; extra == "dev"
Requires-Dist: hypothesis<7,>=6; extra == "dev"
Requires-Dist: pytest<9,>=8; extra == "dev"
Requires-Dist: setuptools<76,>=75; extra == "dev"
Requires-Dist: twine<6,>=5; extra == "dev"
